.gitignore
LICENSE
README.md
requirements.txt
setup.py
re_roll/__init__.py
re_roll/main.py
re_roll.egg-info/PKG-INFO
re_roll.egg-info/SOURCES.txt
re_roll.egg-info/dependency_links.txt
re_roll.egg-info/entry_points.txt
re_roll.egg-info/requires.txt
re_roll.egg-info/top_level.txt