Metadata-Version: 2.1
Name: re-roll
Version: 0.1.0
Summary: CLI-based random encounter roller for Tabletop RPGs
Home-page: https://github.com/ganelonhb/re-roll
Author: Anon TG
Author-email: justyouraveragejoe@outlook.com
License: GPL
Platform: UNKNOWN
Classifier: Programming Language :: Python :: 3
Classifier: License :: OSI Approved :: GNU General Public License v3 (GPLv3)
Classifier: Operating System :: OS Independent
Requires-Python: >=3.9.9
License-File: LICENSE
